dofaucet/__init__.py
dofaucet/ansibleinventory.py
dofaucet/cli.py
dofaucet/dofaucet.py
dofaucet-0.0.2.dist-info/LICENSE
dofaucet-0.0.2.dist-info/METADATA
dofaucet-0.0.2.dist-info/WHEEL
dofaucet-0.0.2.dist-info/entry_points.txt
dofaucet-0.0.2.dist-info/top_level.txt
dofaucet-0.0.2.dist-info/RECORD
