Metadata-Version: 2.1
Name: dofaucet
Version: 0.0.2
Summary: read ansible yaml inventory, create droplets
Home-page: https://github.com/avollmerhaus/dofaucet
Author: Aljoscha Vollmerhaus
Author-email: pydev@aljoscha.vollmerhaus.net
License: UNKNOWN
Platform: UNKNOWN
Classifier: Programming Language :: Python :: 3
Classifier: License :: OSI Approved :: GNU General Public License v3 (GPLv3)
Classifier: Operating System :: POSIX :: Linux
Classifier: Environment :: Console
Requires-Dist: python-digitalocean
Requires-Dist: pyyaml
